3.9.7 (default, Oct 10 2021, 15:13:22) 
[GCC 11.1.0] magic: 610d0d0a
./config.cpython-39.pyc magic: 610d0d0a
timestamp Fri Nov 26 23:21:18 2021 size: 1357
  2           0 LOAD_CONST               0 ('user-agent')

  3           2 LOAD_CONST               1 ('Mozilla/5.0 (Windows NT 10.0; Win64; x64) AppleWebKit/537.36 (KHTML, like Gecko) Chrome/91.0.4472.124 Safari/537.36')

  1           4 BUILD_MAP                1
              6 STORE_NAME               0 (headers)

  6           8 LOAD_CONST               2 ('48006617374')

  8          10 LOAD_CONST               3 ('Apy097ZCCps4raq8Vak6EclcDTnVbRHotrL1kjvg0HhijCiQ5tx1fjNRHoOOepPEF-LGgptwgd60d949_PPNL50.')

 10          12 LOAD_CONST               4 ('_2A25N_5P1DeRhGeBP6VQS8C3JyD-IHXVvAz29rDV6PUJbkdAKLU_ikW1NRWejPY-DN--BzH5MBviwbw_E66Bu54SF')

 12          14 LOAD_CONST               5 ('0033WrSXqPxfM725Ws9jqgMF55529P9D9W5v1ED0B0LiqpSlMv3MxhXd5JpX5KMhUgL.Foqpeoq0ehefe0e2dJLoI7UrUgUf9NHo')

 13          16 LOAD_CONST               6 ('1')

 15          18 LOAD_CONST               7 ('oid%3D4662543623130610%26luicode%3D10000011%26lfid%3D231093_-_selffollowed%26fid%3D231093_-_selffollowed%26uicode%3D10000011')

 16          20 LOAD_CONST               8 ('410d4e')

 17          22 LOAD_CONST               9 ('1110006030')

  5          24 LOAD_CONST              10 (('T_WM', 'SCF', 'SUB', 'SUBP', 'MLOGIN', 'M_WEIBOCN_PARAMS', 'XSRF-TOKEN', 'WEIBOCN_FROM'))
             26 BUILD_CONST_KEY_MAP      8
             28 STORE_NAME               1 (cookies)

 20          30 LOAD_CONST              11 ('http://127.0.0.1:10809')

 21          32 LOAD_CONST              11 ('http://127.0.0.1:10809')

 19          34 LOAD_CONST              12 (('http', 'https'))
             36 BUILD_CONST_KEY_MAP      2
             38 STORE_NAME               2 (proxies)

 40          40 LOAD_CONST              13 ('https://m.weibo.cn/profile/info?uid={id}')
             42 STORE_NAME               3 (info_url)

 41          44 LOAD_CONST              14 ('https://m.weibo.cn/api/container/getIndex?containerid=231051_-_followers_-_{id}')
             46 STORE_NAME               4 (follower_url)

 42          48 LOAD_CONST              15 ('https://m.weibo.cn/api/container/getIndex?containerid=231051_-_fans_-_{id}')
             50 STORE_NAME               5 (fans_url)
             52 LOAD_CONST              16 (None)
             54 RETURN_VALUE
names ('headers', 'cookies', 'proxies', 'info_url', 'follower_url', 'fans_url')
filename /home/gugugu/Source/repo/social-network/config.py
